{
  "id": "01KXNGQYS8997QET0KWJA29B38",
  "target": {
    "type": "tag",
    "id": "req.action-flow.axis-gaps"
  },
  "why": "[#40 ④ 精緻化（B精緻化・doc のみ）] total 軸×no-op 側の偽 L-total への注意書き\n\n対象: req.action-flow.axis-gaps（total 軸の L-total 健全性の境界。DESIGN/`tag create --total --help` への注意書き＝adopt 後に着地）。\n\nWHY: axis-gaps の根拠 decision 01KXMGGD6T0173DZ6HGM0ZVNZ9 は L-total を「唯一 clean に sound」と位置づける。`totalGaps`（internal/flow/analyze.go:449-468）は total=true 軸の値のうち given に現れないものを L-total（抜け）として出す。だが「片側が本質的に no-op（対応 transition が無いのが正しい）」な2値を total にすると、no-op 側が偽の抜けとして出て sound 性が損なわれる。「total にしてよいのは全値が本当に materialize されるべき軸だけ」という authoring 上の境界を doc に明示するのは axis-gaps の delta 精緻化で過去 decision と整合（矛盾なし）。\n\n⚠️スコープ外（別 spec-first で扱う）: `acknowledged-empty`（意図的に空な値の宣言機構）は今回入れない。これは model.Axis/Tag への additive フィールド＝コアモデル変更であり、かつ L-total の sound 性を弱めうる（意図的空値を抜けから除外＝false negative 化のリスク）。acknowledged-remainder（decision 01KXMGH6ND8N7CQ4A4J9JZPKM0）の正本化とまとめて慎重に spec-first で扱うべき。今回は「no-op 側を持つ2値は total 軸にしない」注意書きのみ。\n\nadopt 後の実装（doc のみ）: DESIGN §3.4（total の説明）と `pmem tag create --total`/`tag edit --total` の --help に「no-op 側（対応 transition が無いのが正しい値）を持つ2値は total 軸にしない — 非 total にするか、分割で表す」旨を注意書きとして1文足す。コアモデル変更なし。",
  "at": "2026-07-16T13:09:35Z",
  "commits": [
    "8fe854d7f902ad4c97ed3853ac723ebd82fe8dac"
  ]
}
